arxivtorm/__init__.py
arxivtorm/main.py
arxivtorm-0.1.4.dist-info/LICENSE
arxivtorm-0.1.4.dist-info/METADATA
arxivtorm-0.1.4.dist-info/WHEEL
arxivtorm-0.1.4.dist-info/entry_points.txt
arxivtorm-0.1.4.dist-info/top_level.txt
arxivtorm-0.1.4.dist-info/RECORD
