Metadata-Version: 2.1
Name: arxivtorm
Version: 0.1.4
Summary: Gets papers from ArXiv and puts them on your remarkable
Home-page: https://github.com/narendasan/ArXivToRm
Author: Naren Dasan
Author-email: naren@narendasan.com
License: NCSA
Platform: UNKNOWN
Requires-Dist: arxiv (==1.4.2)
